applier/__init__.py
applier/app.py
applier/commands.py
applier/config.py
applier/security.py
applier/tasks.py
applier-0.4.0.dist-info/METADATA
applier-0.4.0.dist-info/WHEEL
applier-0.4.0.dist-info/RECORD
