Metadata-Version: 2.1
Name: applier
Version: 0.4.0
Summary: Automatically apply SaltStack highstate on webhooks
Author: Alex Krantz
Author-email: alex@krantz.dev
Requires-Python: >=3.9,<4.0
Classifier: Programming Language :: Python :: 3
Classifier: Programming Language :: Python :: 3.9
Classifier: Programming Language :: Python :: 3.10
Classifier: Programming Language :: Python :: 3.11
Requires-Dist: cachetools (>=5.3.0,<6.0.0)
Requires-Dist: dramatiq[redis] (>=1.14.1,<2.0.0)
Requires-Dist: flask (>=2.2.2,<3.0.0)
Requires-Dist: gunicorn (>=20.1.0,<21.0.0)
Requires-Dist: importlib-metadata (>=3.6.0,<4.0.0)
Requires-Dist: salt (>=3005.1,<3006.0)
